AUTHORS.rst
CONTRIBUTING.rst
HISTORY.rst
LICENSE
MANIFEST.in
README.rst
setup.cfg
setup.py
cid/__init__.py
cid/apps.py
cid/context_processors.py
cid/cursor.py
cid/locals.py
cid/log.py
cid/middleware.py
cid/models.py
cid/backends/__init__.py
cid/backends/mysql/__init__.py
cid/backends/mysql/base.py
cid/backends/oracle/__init__.py
cid/backends/oracle/base.py
cid/backends/postgresql/__init__.py
cid/backends/postgresql/base.py
cid/backends/sqlite3/__init__.py
cid/backends/sqlite3/base.py
mbq_django_cid.egg-info/PKG-INFO
mbq_django_cid.egg-info/SOURCES.txt
mbq_django_cid.egg-info/dependency_links.txt
mbq_django_cid.egg-info/not-zip-safe
mbq_django_cid.egg-info/top_level.txt