Metadata-Version: 1.1
Name: mbq-django-cid
Version: 0.2.2
Summary: Correlation IDs in Django for debugging requests
Home-page: https://github.com/snowball-digital/cid
Author: Snowball One
Author-email: opensource@snowballone.com.au
License: BSD
Keywords: cid
Platform: UNKNOWN
Classifier: Development Status :: 2 - Pre-Alpha
Classifier: Framework :: Django
Classifier: Intended Audience :: Developers
Classifier: License :: OSI Approved :: BSD License
Classifier: Natural Language :: English
Classifier: Programming Language :: Python :: 2
Classifier: Programming Language :: Python :: 2.6
Classifier: Programming Language :: Python :: 2.7
Classifier: Programming Language :: Python :: 3
Classifier: Programming Language :: Python :: 3.3
Classifier: Programming Language :: Python :: 3.4
